MANIFEST.in
README.txt
requirements.txt
setup.py
howfo/__init__.py
howfo/config.py
howfo/const.py
howfo/error.py
howfo/helpers.py
howfo/logger.py
howfo/plugins.py
howfo/tools.py
howfo/config/app.json
howfo/config/const.py
howfo/config/custom.json
howfo/config/log.json
howfo/config/structure.json
howfo/tpl/__init__.tpl
howfo/tpl/config.tpl
howfo/tpl/conftest.tpl
howfo/tpl/demo_plugin.tpl
howfo/tpl/docker-compose.tpl
howfo/tpl/error.tpl
howfo/tpl/gunicorn.tpl
howfo/tpl/hello_controller.tpl
howfo/tpl/hello_handler.tpl
howfo/tpl/requirements.tpl
howfo/tpl/router.tpl
howfo/tpl/server.tpl
howfo/tpl/start.tpl
howfo/tpl/test_api.tpl
howfo/tpl/test_db.tpl
howfo/tpl/tools.tpl
howfo/tpl/user_model.tpl
howfo_frame.egg-info/PKG-INFO
howfo_frame.egg-info/SOURCES.txt
howfo_frame.egg-info/dependency_links.txt
howfo_frame.egg-info/not-zip-safe
howfo_frame.egg-info/requires.txt
howfo_frame.egg-info/top_level.txt