Metadata-Version: 1.1
Name: howfo-frame
Version: 1.0.1
Summary: A simple example of how to layout a small site quickly
Home-page: http://www.howfo.net
Author: kalaiya86
Author-email: kalaiya86@gmail.com
License: UNKNOWN
Keywords: howfo-frame
Platform: any
Classifier: Development Status :: 3 - Alpha
Classifier: Topic :: Utilities
Classifier: License :: OSI Approved :: MIT License
Classifier: Programming Language :: Python :: 3
